vanpy/__init__.py
vanpy/core/BasePipeline.py
vanpy/core/ClassificationPipeline.py
vanpy/core/ComponentPayload.py
vanpy/core/FeatureExtractionPipeline.py
vanpy/core/ModelInferencePipeline.py
vanpy/core/Pipeline.py
vanpy/core/PipelineComponent.py
vanpy/core/PreprocessPipeline.py
vanpy/core/__init__.py
vanpy/core/feature_extraction_components/LibrosaFeaturesExtractor.py
vanpy/core/feature_extraction_components/PyannoteEmbedding.py
vanpy/core/feature_extraction_components/SpeechBrainEmbedding.py
vanpy/core/feature_extraction_components/VanpySpeakerEmbedding.py
vanpy/core/feature_extraction_components/__init__.py
vanpy/core/model_inference_components/AgglomerativeClusterer.py
vanpy/core/model_inference_components/AgglomerativeDiarizationClassifier.py
vanpy/core/model_inference_components/BaseClassificationComponent.py
vanpy/core/model_inference_components/CVAgeClassifier.py
vanpy/core/model_inference_components/CVGenderClassifier.py
vanpy/core/model_inference_components/CosineDiarizationClassifier.py
vanpy/core/model_inference_components/CosineDistanceClusterer.py
vanpy/core/model_inference_components/GMMClusterer.py
vanpy/core/model_inference_components/GMMDiarizationClassifier.py
vanpy/core/model_inference_components/IEMOCAPEmotionClassifier.py
vanpy/core/model_inference_components/RavdessEmotionClassifier.py
vanpy/core/model_inference_components/VanpyAgeRegressor.py
vanpy/core/model_inference_components/VanpyEmotionClassifier.py
vanpy/core/model_inference_components/VanpyGenderClassifier.py
vanpy/core/model_inference_components/VanpyHeightRegressor.py
vanpy/core/model_inference_components/VoxcelebAgeRegressor.py
vanpy/core/model_inference_components/VoxcelebGenderClassifier.py
vanpy/core/model_inference_components/VoxcelebHeightRegressor.py
vanpy/core/model_inference_components/Wav2Vec2ADV.py
vanpy/core/model_inference_components/Wav2Vec2STT.py
vanpy/core/model_inference_components/WhisperAT.py
vanpy/core/model_inference_components/WhisperSTT.py
vanpy-0.92.14.dist-info/LICENSE
vanpy-0.92.14.dist-info/METADATA
vanpy-0.92.14.dist-info/WHEEL
vanpy-0.92.14.dist-info/dependency_links.txt
vanpy-0.92.14.dist-info/top_level.txt
vanpy-0.92.14.dist-info/zip-safe
vanpy-0.92.14.dist-info/RECORD
