Metadata-Version: 2.1
Name: vanpy
Version: 0.92.14
Summary: VANPY - Voice Analysis framework in Python
Author: Gregory Koushnir
Author-email: koushgre@post.bgu.ac.il
License: Apache License v2.0
Platform: unix
Platform: linux
Platform: osx
Platform: cygwin
Platform: win32
Classifier: Programming Language :: Python :: 3
Classifier: Programming Language :: Python :: 3 :: Only
Classifier: Programming Language :: Python :: 3.8
Classifier: Programming Language :: Python :: 3.9
Requires-Python: >=3.8
License-File: LICENSE
Requires-Dist: gdown (==4.4.0)
Requires-Dist: huggingface-hub (==0.8.1)
Requires-Dist: keras (==2.8.0)
Requires-Dist: librosa (==0.9.1)
Requires-Dist: pandas (==1.3.5)
Requires-Dist: pydub (==0.25.1)
Requires-Dist: PyYAML (==6.0)
Requires-Dist: scikit-learn (==1.0.2)
Requires-Dist: speechbrain (==0.5.13)
Requires-Dist: torch (==1.13.1)
Requires-Dist: torchaudio (==0.13.1)
Provides-Extra: all
Requires-Dist: openai-whisper (==20230314) ; extra == 'all'
Requires-Dist: inaSpeechSegmenter (==0.7.3) ; extra == 'all'
Requires-Dist: pyannote.audio (==2.1.1) ; extra == 'all'
Requires-Dist: soundfile (==0.10.3.post1) ; extra == 'all'
Requires-Dist: tensorflow (==2.8.0) ; extra == 'all'
Requires-Dist: tensorflow-hub (==0.13.0) ; extra == 'all'
Requires-Dist: transformers (==4.19.2) ; extra == 'all'
Requires-Dist: speechbrain (==0.5.13) ; extra == 'all'
Provides-Extra: ina
Requires-Dist: inaSpeechSegmenter (==0.7.3) ; extra == 'ina'
Provides-Extra: pyannote
Requires-Dist: pyannote.audio (==2.1.1) ; extra == 'pyannote'
Requires-Dist: soundfile (==0.10.3.post1) ; extra == 'pyannote'
Provides-Extra: speech_brain_iemocap_emotion
Requires-Dist: speechbrain (==0.5.13) ; extra == 'speech_brain_iemocap_emotion'
Requires-Dist: transformers (==4.19.2) ; extra == 'speech_brain_iemocap_emotion'
Provides-Extra: wav2vec2
Requires-Dist: transformers (==4.19.2) ; extra == 'wav2vec2'
Provides-Extra: whisper
Requires-Dist: openai-whisper (==20230314) ; extra == 'whisper'
Provides-Extra: yamnet
Requires-Dist: tensorflow (==2.8.0) ; extra == 'yamnet'
Requires-Dist: tensorflow-hub (==0.13.0) ; extra == 'yamnet'
